typed_input.py
typed_input-1.3.1.dist-info/METADATA
typed_input-1.3.1.dist-info/WHEEL
typed_input-1.3.1.dist-info/licenses/LICENSE
typed_input-1.3.1.dist-info/RECORD
