Metadata-Version: 2.3
Name: typed-input
Version: 1.3.1
Summary: Effortless type-safe user input for integers, floats, dates, and more...
Project-URL: Homepage, https://github.com/sashsinha/typed_input
Project-URL: Documentation, https://github.com/sashsinha/typed_input/blob/main/README.md
Project-URL: Repository, https://github.com/sashsinha/typed_input.git
Author-email: Sash Sinha <sashsinha1@gmail.com>
Maintainer-email: Sash Sinha <sashsinha1@gmail.com>
License: MIT License
Keywords: input,input-validation,typing,utilities
Classifier: Development Status :: 5 - Production/Stable
Classifier: Intended Audience :: Developers
Classifier: License :: OSI Approved :: MIT License
Classifier: Operating System :: MacOS
Classifier: Operating System :: Microsoft :: Windows
Classifier: Operating System :: POSIX :: Linux
Classifier: Programming Language :: Python
Classifier: Programming Language :: Python :: 3.9
Classifier: Programming Language :: Python :: 3.10
Classifier: Programming Language :: Python :: 3.11
Classifier: Programming Language :: Python :: 3.12
Classifier: Programming Language :: Python :: 3.13
Classifier: Topic :: Utilities
Requires-Python: >=3.9
Provides-Extra: dev
Requires-Dist: mypy>=1.13.0; extra == 'dev'
Requires-Dist: ruff>=0.7.4; extra == 'dev'
Provides-Extra: test
Requires-Dist: parameterized; extra == 'test'
